PyMapKit/Map.py
PyMapKit/RasterLayer.py
PyMapKit/TextLayer.py
PyMapKit/TileLayer.py
PyMapKit/VectorLayer.py
PyMapKit/__init__.py
PyMapKit/backend/CairoBackend.py
PyMapKit/backend/TkBackend.py
PyMapKit/backend/__init__.py
PyMapKit-0.1.4.dist-info/LICENSE.txt
PyMapKit-0.1.4.dist-info/METADATA
PyMapKit-0.1.4.dist-info/WHEEL
PyMapKit-0.1.4.dist-info/top_level.txt
PyMapKit-0.1.4.dist-info/RECORD
