Metadata-Version: 2.1
Name: PyMapKit
Version: 0.1.4
Summary: A Python based open-source mapping toolkit
Home-page: https://github.com/BenKnisley/PyMapKit
Author: Ben Knisley
Author-email: benknisley@gmail.com
License: MIT
Keywords: GIS Geography GeoSpatial MapTiles PyMapKit
Platform: UNKNOWN
Classifier: Development Status :: 1 - Planning
Classifier: Topic :: Scientific/Engineering :: GIS
Classifier: License :: OSI Approved :: MIT License
Classifier: Operating System :: POSIX :: Linux
Classifier: Programming Language :: Python :: 3.6
Requires-Dist: pyproj
Requires-Dist: numpy
Requires-Dist: requests
Requires-Dist: pillow
